{
  "metadata": {
    "title": "HGP 5.º — Primeiros Povos e Romanização",
    "subtitle": "Da Pré‑História à presença romana na Península Ibérica",
    "description": "Modos de vida, castros, romanização e legado romano em Portugal.",
    "unit": "HGP5_PPROM",
    "version": "v1",
    "footer": "Alinhado com as AE de HGP (5.º ano)."
  },
  "cards": [
    {
      "id": 1,
      "tema": "Pré‑História",
      "curto": false,
      "q": "Distingue comunidades recoletoras de comunidades agro‑pastoris.",
      "a": "Recoletoras eram nómadas, viviam da caça, pesca e recolha; agro‑pastoris eram sedentárias e praticavam agricultura e pastorícia."
    },
    {
      "id": 2,
      "tema": "Castreja",
      "curto": true,
      "q": "Que características identificas num castro?",
      "a": "Povoado fortificado em elevação, com muralhas e casas circulares."
    },
    {
      "id": 3,
      "tema": "Povos",
      "curto": false,
      "q": "Quem eram os Lusitanos e que figura se destaca na sua resistência?",
      "a": "Povo da fachada ocidental peninsular; destaca‑se Viriato na resistência a Roma."
    },
    {
      "id": 4,
      "tema": "Romanização",
      "curto": true,
      "q": "O que se entende por romanização?",
      "a": "Processo de adoção de elementos romanos (língua, leis, cidades, vias, cultura) pelos povos locais."
    },
    {
      "id": 5,
      "tema": "Vias romanas",
      "curto": false,
      "q": "Para que serviam as vias romanas?",
      "a": "Ligar cidades, facilitar deslocações de exércitos, comércio e administração."
    },
    {
      "id": 6,
      "tema": "Cidade romana",
      "curto": true,
      "q": "Indica dois elementos de uma cidade romana.",
      "a": "Fórum e termas (entre outros: anfiteatro, aqueduto, templos)."
    },
    {
      "id": 7,
      "tema": "Língua e legado",
      "curto": false,
      "q": "Que legado romano permanece na cultura portuguesa?",
      "a": "A língua portuguesa de base latina, direito romano, traçado de cidades e pontes, calendário."
    },
    {
      "id": 8,
      "tema": "Economia",
      "curto": false,
      "q": "Que atividades económicas eram comuns na Lusitânia romana?",
      "a": "Agricultura (cereais, vinho, azeite), mineração e comércio."
    },
    {
      "id": 9,
      "tema": "Fontes históricas",
      "curto": true,
      "q": "Dá um exemplo de fonte histórica material romana em Portugal.",
      "a": "Ponte de Chaves (Aquae Flaviae), ruínas de Conímbriga ou Milreu."
    },
    {
      "id": 10,
      "tema": "Religião",
      "curto": false,
      "q": "Como se relacionou a religião romana com as crenças locais?",
      "a": "Houve sincretismo: deuses romanos associaram‑se a divindades locais."
    },
    {
      "id": 11,
      "tema": "Administração",
      "curto": true,
      "q": "Como se chamavam as grandes divisões administrativas romanas?",
      "a": "Províncias (ex.: Lusitânia)."
    },
    {
      "id": 12,
      "tema": "Fim do Império",
      "curto": false,
      "q": "Quem foram os povos que se instalaram na Península após o declínio romano?",
      "a": "Povos germânicos como Suevos e Visigodos."
    }
  ],
  "distractors": {
    "1": [
      "Recoletoras viviam em cidades grandes",
      "Agro‑pastoris eram nómadas que não cultivavam",
      "Recoletoras produziam vinho e azeite"
    ],
    "2": [
      "Povoado aberto em planície",
      "Vilas romanas com mosaicos",
      "Cidade com arruamentos ortogonais"
    ],
    "3": [
      "Povo romano do norte de África",
      "Chefes cartagineses na Península",
      "Guerreiro grego fundador de Lisboa"
    ],
    "4": [
      "Conquista militar dos povos por Roma",
      "Fuga dos romanos da Península",
      "Adoção de costumes locais pelos romanos"
    ],
    "5": [
      "Apenas para corridas de carros",
      "Serviam só para condução de água",
      "Eram templos religiosos"
    ],
    "6": [
      "Arranha‑céus",
      "Faróis modernos",
      "Castelos medievais"
    ],
    "7": [
      "Adoção do grego como língua oficial",
      "Desaparecimento total das pontes romanas",
      "Calendário lunar exclusivamente"
    ],
    "8": [
      "Pesca da baleia em larga escala",
      "Plantação de café",
      "Exploração de petróleo"
    ],
    "9": [
      "Capelas barrocas",
      "Mosteiros medievais",
      "Castelos templários"
    ],
    "10": [
      "Proibição total de cultos locais",
      "Religião única e imutável em todo o Império",
      "Conversão imediata ao cristianismo em toda a Península"
    ],
    "11": [
      "Concelhos medievais",
      "Distritos portugueses atuais",
      "Feudos da Idade Média"
    ],
    "12": [
      "Árabes e Otomanos no século II",
      "Mongóis e Hunos",
      "Vikings em permanência no interior"
    ]
  },
  "trueFalse": [
    {
      "t": "Os povos castrejos construíam povoados fortificados em elevações.",
      "v": true,
      "e": "Daí o nome «castros» e as muralhas."
    },
    {
      "t": "A romanização implicou a adoção de hábitos, línguas e leis romanas.",
      "v": true,
      "e": "Processo cultural e administrativo."
    },
    {
      "t": "As vias romanas tinham função apenas religiosa.",
      "v": false,
      "e": "Serviam sobretudo a administração, o comércio e o exército."
    },
    {
      "t": "O português tem origem maioritariamente latina.",
      "v": true,
      "e": "É uma língua românica."
    },
    {
      "t": "Após Roma, instalaram‑se na Península povos germânicos.",
      "v": true,
      "e": "Suevos e Visigodos, entre outros."
    },
    {
      "t": "Viriato foi um líder romano na Lusitânia.",
      "v": false,
      "e": "Foi líder lusitano que resistiu aos romanos."
    },
    {
      "t": "Conímbriga é um importante sítio arqueológico romano em Portugal.",
      "v": true,
      "e": "Conserva muralhas, casas e mosaicos."
    },
    {
      "t": "A religião romana nunca se misturou com crenças locais.",
      "v": false,
      "e": "Houve sincretismo religioso."
    }
  ]
}